job_worth_calculator_mcp/__init__.py
job_worth_calculator_mcp/main.py
job_worth_calculator_mcp-1.0.0.dist-info/licenses/LICENSE
job_worth_calculator_mcp-1.0.0.dist-info/METADATA
job_worth_calculator_mcp-1.0.0.dist-info/WHEEL
job_worth_calculator_mcp-1.0.0.dist-info/entry_points.txt
job_worth_calculator_mcp-1.0.0.dist-info/top_level.txt
job_worth_calculator_mcp-1.0.0.dist-info/RECORD
