Metadata-Version: 2.4
Name: job-worth-calculator-mcp
Version: 1.0.0
Summary: 基于worth-calculator的全面工作性价比计算MCP工具
Home-page: https://github.com/ai/job-worth-calculator-mcp
Author: AI助手
Author-email: ai@example.com
Project-URL: Bug Reports, https://github.com/ai/job-worth-calculator-mcp/issues
Project-URL: Source, https://github.com/ai/job-worth-calculator-mcp
Keywords: mcp,job,worth,calculator,salary,comparison,career
Classifier: Development Status :: 4 - Beta
Classifier: Intended Audience :: Developers
Classifier: Intended Audience :: End Users/Desktop
Classifier: License :: OSI Approved :: MIT License
Classifier: Operating System :: OS Independent
Classifier: Programming Language :: Python :: 3
Classifier: Programming Language :: Python :: 3.8
Classifier: Programming Language :: Python :: 3.9
Classifier: Programming Language :: Python :: 3.10
Classifier: Programming Language :: Python :: 3.11
Classifier: Programming Language :: Python :: 3.12
Classifier: Topic :: Office/Business :: Financial
Classifier: Topic :: Software Development :: Libraries :: Python Modules
Requires-Python: >=3.8
License-File: LICENSE
Requires-Dist: mcp>=1.0.0
Requires-Dist: fastmcp>=0.1.0
Dynamic: author
Dynamic: author-email
Dynamic: classifier
Dynamic: description
Dynamic: description-content-type
Dynamic: home-page
Dynamic: keywords
Dynamic: license-file
Dynamic: project-url
Dynamic: requires-dist
Dynamic: requires-python
Dynamic: summary
